commandpack/__init__.py
commandpack/executors.py
commandpack/factories.py
commandpack/tools.py
commandpack-0.3.2.dist-info/licenses/LICENSE
commandpack-0.3.2.dist-info/METADATA
commandpack-0.3.2.dist-info/WHEEL
commandpack-0.3.2.dist-info/top_level.txt
commandpack-0.3.2.dist-info/RECORD
